toolkit/__init__.py
toolkit/base/__init__.py
toolkit/base/kex.py
toolkit/base/metadata.py
toolkit/base/step.py
toolkit/base/table.py
toolkit/dags/__init__.py
toolkit/dags/dag_project.py
toolkit/dags/dag_project_custom_dags.py
toolkit/dags/dag_project_update.py
toolkit/dags/dag_sandbox.py
toolkit/dags/dag_sharing.py
toolkit/dags/dag_telemetry.py
toolkit/dags/helpers/__init__.py
toolkit/dags/helpers/base.py
toolkit/dags/helpers/datamarts.py
toolkit/dags/helpers/dummies.py
toolkit/dags/helpers/extractors.py
toolkit/dags/helpers/orchestrations.py
toolkit/dags/helpers/pools.py
toolkit/dags/helpers/refresh_sharing.py
toolkit/dags/helpers/sandboxes.py
toolkit/dags/helpers/telemetry.py
toolkit/dags/helpers/template.html
toolkit/dags/helpers/transformations.py
toolkit/dags/helpers/upgrade_project.py
toolkit/dags/helpers/utils.py
toolkit/dags/helpers/writers.py
toolkit/executors/__init__.py
toolkit/executors/base/__init__.py
toolkit/executors/base/base.py
toolkit/executors/base/docker.py
toolkit/executors/base/sql.py
toolkit/executors/extractor/__init__.py
toolkit/executors/extractor/docker.py
toolkit/executors/transformation/__init__.py
toolkit/executors/transformation/azure_sql.py
toolkit/executors/transformation/base_sql.py
toolkit/executors/transformation/bq_sql.py
toolkit/executors/transformation/docker.py
toolkit/executors/transformation/postgre_sql.py
toolkit/executors/transformation/redshift_sql.py
toolkit/executors/transformation/snowflake_sql.py
toolkit/executors/writer/__init__.py
toolkit/executors/writer/docker.py
toolkit/managers/__init__.py
toolkit/managers/component/__init__.py
toolkit/managers/component/base.py
toolkit/managers/component/bizztreat_gitlab_docker.py
toolkit/managers/component/docker.py
toolkit/managers/component/docker_build.py
toolkit/managers/component/docker_pull.py
toolkit/managers/component/git_docker.py
toolkit/managers/component/local_storage_docker.py
toolkit/managers/component/sql.py
toolkit/managers/configuration/__init__.py
bizzflow_toolkit-2.3.0.dev5.dist-info/LICENSE.md
bizzflow_toolkit-2.3.0.dev5.dist-info/WHEEL
bizzflow_toolkit-2.3.0.dev5.dist-info/METADATA
bizzflow_toolkit-2.3.0.dev5.dist-info/RECORD
