Metadata-Version: 2.1
Name: bizzflow-toolkit
Version: 2.3.0.dev5
Summary: Bizzflow is ETL (extract - transform - load) template based on standard native cloud services. Supporting the three main cloud providers (Google Cloud Platform / Amazon AWS / MS Azure), it takes all the advantages. You pay only for services you really use. Perfect for teams who want to have direct relationship with their cloud provider. No matter if it is because of security or because you already have existing contract.
Home-page: https://www.bizzflow.net/
License: Apache-2.0
Author: Bizztreat
Author-email: owner@bizzflow.net
Requires-Python: >=3.6,<4.0
Classifier: License :: OSI Approved :: Apache Software License
Classifier: Programming Language :: Python :: 3
Classifier: Programming Language :: Python :: 3.10
Classifier: Programming Language :: Python :: 3.6
Classifier: Programming Language :: Python :: 3.7
Classifier: Programming Language :: Python :: 3.8
Classifier: Programming Language :: Python :: 3.9
Requires-Dist: PyYAML (>=6.0,<7.0)
Requires-Dist: boto3 (<1.16)
Requires-Dist: cffi (==1.14.0)
Requires-Dist: fabric (>=2.5.0,<3.0.0)
Requires-Dist: invoke (>=1.4.1,<2.0.0)
Requires-Dist: jsonschema (>=3.2.0,<3.3.0)
Requires-Dist: paramiko (>=2.7.2,<3.0.0)
Requires-Dist: pyodbc (>=4.0.30,<5.0.0)
Requires-Dist: python3-openid (>=3.2.0,<4.0.0)
Requires-Dist: redshift-connector (>=2.0.907,<3.0.0)
Requires-Dist: retry_helper (>=0.0.4,<0.0.5)
Requires-Dist: sqlparse (>=0.4.1,<0.5.0)
Requires-Dist: statsd (>=3.3.0,<4.0.0)
Project-URL: Documentation, https://wiki.bizzflow.net/
Project-URL: Repository, https://gitlab.com/bizzflow-etl/toolkit
